banana/__init__.py
banana/__init__.pyi
banana/_assign_if_missing.py
banana/_config.py
banana/_entrypoint.py
banana/_start_time.py
banana/env/__init__.py
banana/env/__init__.pyi
banana/env/_bool.py
banana/env/_str.py
banana/git/__init__.py
banana/git/__init__.pyi
banana/git/_auto_commit.py
banana/git/_repo.py
banana/git/_root.py
banana/integration/__init__.py
banana/integration/__init__.pyi
banana/integration/base/__init__.py
banana/integration/base/__init__.pyi
banana/integration/base/_integration.py
banana/integration/comet/__init__.py
banana/integration/comet/__init__.pyi
banana/integration/comet/_comet.py
banana/integration/core/__init__.py
banana/integration/core/__init__.pyi
banana/integration/core/_banana.py
banana/integration/core/_main.py
banana/integration/git/__init__.py
banana/integration/git/__init__.pyi
banana/integration/git/_git.py
banana/integration/restic/__init__.py
banana/integration/restic/__init__.pyi
banana/integration/restic/_restic.py
liblaf_banana-0.1.1.dist-info/METADATA
liblaf_banana-0.1.1.dist-info/WHEEL
liblaf_banana-0.1.1.dist-info/licenses/LICENSE
liblaf_banana-0.1.1.dist-info/RECORD
