Metadata-Version: 2.4
Name: liblaf-banana
Version: 0.1.1
Summary: Add your description here
Project-URL: Changelog, https://github.com/liblaf/banana/blob/main/CHANGELOG.md
Project-URL: Homepage, https://github.com/liblaf/banana
Project-URL: Issue Tracker, https://github.com/liblaf/banana/issues
Project-URL: Release Notes, https://github.com/liblaf/banana/releases
Project-URL: Source Code, https://github.com/liblaf/banana
Author-email: liblaf <30631553+liblaf@users.noreply.github.com>
License-Expression: MIT
License-File: LICENSE
Requires-Python: ~=3.12
Requires-Dist: gitpython~=3.1.44
Requires-Dist: glom~=24.11.0
Requires-Dist: lazy-loader~=0.4
Requires-Dist: liblaf-avocado~=0.1.0
Requires-Dist: loguru~=0.7.3
Requires-Dist: pydantic-settings~=2.7.1
Provides-Extra: comet
Requires-Dist: comet-ml~=3.47.6; extra == 'comet'
